lingkar33423321/__init__.py
lingkar33423321/my_class.py
linkar33423321-0.0.1.dist-info/LICENSE.TXT
linkar33423321-0.0.1.dist-info/METADATA
linkar33423321-0.0.1.dist-info/WHEEL
linkar33423321-0.0.1.dist-info/top_level.txt
linkar33423321-0.0.1.dist-info/RECORD
